jgtpyalgotrade/__init__.py
jgtpyalgotrade/bar.py
jgtpyalgotrade/dispatcher.py
jgtpyalgotrade/dispatchprio.py
jgtpyalgotrade/eventprofiler.py
jgtpyalgotrade/logger.py
jgtpyalgotrade/marketsession.py
jgtpyalgotrade/observer.py
jgtpyalgotrade/plotter.py
jgtpyalgotrade/resamplebase.py
jgtpyalgotrade/warninghelpers.py
jgtpyalgotrade/barfeed/__init__.py
jgtpyalgotrade/barfeed/common.py
jgtpyalgotrade/barfeed/csvfeed.py
jgtpyalgotrade/barfeed/dbfeed.py
jgtpyalgotrade/barfeed/googlefeed.py
jgtpyalgotrade/barfeed/membf.py
jgtpyalgotrade/barfeed/ninjatraderfeed.py
jgtpyalgotrade/barfeed/quandlfeed.py
jgtpyalgotrade/barfeed/resampled.py
jgtpyalgotrade/barfeed/sqlitefeed.py
jgtpyalgotrade/barfeed/yahoofeed.py
jgtpyalgotrade/bitcoincharts/__init__.py
jgtpyalgotrade/bitcoincharts/barfeed.py
jgtpyalgotrade/bitstamp/__init__.py
jgtpyalgotrade/bitstamp/barfeed.py
jgtpyalgotrade/bitstamp/broker.py
jgtpyalgotrade/bitstamp/common.py
jgtpyalgotrade/bitstamp/httpclient.py
jgtpyalgotrade/bitstamp/livebroker.py
jgtpyalgotrade/bitstamp/livefeed.py
jgtpyalgotrade/bitstamp/wsclient.py
jgtpyalgotrade/broker/__init__.py
jgtpyalgotrade/broker/backtesting.py
jgtpyalgotrade/broker/fillstrategy.py
jgtpyalgotrade/broker/slippage.py
jgtpyalgotrade/dataseries/__init__.py
jgtpyalgotrade/dataseries/aligned.py
jgtpyalgotrade/dataseries/bards.py
jgtpyalgotrade/dataseries/resampled.py
jgtpyalgotrade/feed/__init__.py
jgtpyalgotrade/feed/csvfeed.py
jgtpyalgotrade/feed/memfeed.py
jgtpyalgotrade/optimizer/__init__.py
jgtpyalgotrade/optimizer/base.py
jgtpyalgotrade/optimizer/local.py
jgtpyalgotrade/optimizer/serialization.py
jgtpyalgotrade/optimizer/server.py
jgtpyalgotrade/optimizer/worker.py
jgtpyalgotrade/optimizer/xmlrpcserver.py
jgtpyalgotrade/stratanalyzer/__init__.py
jgtpyalgotrade/stratanalyzer/drawdown.py
jgtpyalgotrade/stratanalyzer/returns.py
jgtpyalgotrade/stratanalyzer/sharpe.py
jgtpyalgotrade/stratanalyzer/trades.py
jgtpyalgotrade/strategy/__init__.py
jgtpyalgotrade/strategy/position.py
jgtpyalgotrade-0.22.dist-info/LICENSE
jgtpyalgotrade-0.22.dist-info/METADATA
jgtpyalgotrade-0.22.dist-info/WHEEL
jgtpyalgotrade-0.22.dist-info/top_level.txt
jgtpyalgotrade-0.22.dist-info/RECORD
